Metadata-Version: 1.1
Name: ezlocale
Version: 0.5
Summary: Easier localization, so everyone can use your programs.
Home-page: https://github.com/reshanie/ezlocale/
Author: Patrick Dill
Author-email: jamespatrickdill@gmail.com
License: MIT
Download-URL: http://github.com/reshanie/ezlocale/archive/master.tar.gz
Keywords: translate locale localization translator gettext
Platform: UNKNOWN
Classifier: Development Status :: 4 - Beta
Classifier: Intended Audience :: Developers
Classifier: Programming Language :: Python :: 3.3
Classifier: Programming Language :: Python :: 3.4
Classifier: Programming Language :: Python :: 3.5
Classifier: Programming Language :: Python :: 3.6
